rusty_tree-1.0.0.dist-info/METADATA
rusty_tree-1.0.0.dist-info/WHEEL
rusty_tree.libs/libevent-2-59c90568.1.so.7
rusty_tree.libs/libevent_pthreads-2-64f9cad0.1.so.7
rusty_tree.libs/libopen-pal-f508c7a5.so.40
rusty_tree.libs/libopen-rte-222f852f.so.40
rusty_tree.libs/libhwloc-a241ead3.so.15
rusty_tree.libs/libltdl-38a07461.so.7
rusty_tree.libs/libudev-8604d606.so.1
rusty_tree.libs/libmpi-b9f74218.so.40
rusty_tree/__init__.py
rusty_tree/types/__init__.py
rusty_tree/types/morton.py
rusty_tree/types/domain.py
rusty_tree/types/point.py
rusty_tree/types/iterator.py
rusty_tree/constants.py
rusty_tree/rusty_tree/__init__.py
rusty_tree/rusty_tree/ffi.py
rusty_tree/distributed.py
rusty_tree/rusty_tree/__init__.py
rusty_tree/rusty_tree/ffi.py
rusty_tree/rusty_tree/native.so
rusty_tree-1.0.0.dist-info/RECORD
